aa_bulletin_board/__init__.py
aa_bulletin_board/app_settings.py
aa_bulletin_board/apps.py
aa_bulletin_board/auth_hooks.py
aa_bulletin_board/forms.py
aa_bulletin_board/managers.py
aa_bulletin_board/models.py
aa_bulletin_board/providers.py
aa_bulletin_board/urls.py
aa_bulletin_board/views.py
aa_bulletin_board/helper/__init__.py
aa_bulletin_board/helper/string.py
aa_bulletin_board/locale/django.pot
aa_bulletin_board/locale/cs_CZ/LC_MESSAGES/django.mo
aa_bulletin_board/locale/cs_CZ/LC_MESSAGES/django.po
aa_bulletin_board/locale/de/LC_MESSAGES/django.mo
aa_bulletin_board/locale/de/LC_MESSAGES/django.po
aa_bulletin_board/locale/es/LC_MESSAGES/django.mo
aa_bulletin_board/locale/es/LC_MESSAGES/django.po
aa_bulletin_board/locale/fr_FR/LC_MESSAGES/django.mo
aa_bulletin_board/locale/fr_FR/LC_MESSAGES/django.po
aa_bulletin_board/locale/it_IT/LC_MESSAGES/django.mo
aa_bulletin_board/locale/it_IT/LC_MESSAGES/django.po
aa_bulletin_board/locale/ja/LC_MESSAGES/django.mo
aa_bulletin_board/locale/ja/LC_MESSAGES/django.po
aa_bulletin_board/locale/ko_KR/LC_MESSAGES/django.mo
aa_bulletin_board/locale/ko_KR/LC_MESSAGES/django.po
aa_bulletin_board/locale/nl_NL/LC_MESSAGES/django.mo
aa_bulletin_board/locale/nl_NL/LC_MESSAGES/django.po
aa_bulletin_board/locale/pl_PL/LC_MESSAGES/django.mo
aa_bulletin_board/locale/pl_PL/LC_MESSAGES/django.po
aa_bulletin_board/locale/ru/LC_MESSAGES/django.mo
aa_bulletin_board/locale/ru/LC_MESSAGES/django.po
aa_bulletin_board/locale/sk/LC_MESSAGES/django.mo
aa_bulletin_board/locale/sk/LC_MESSAGES/django.po
aa_bulletin_board/locale/uk/LC_MESSAGES/django.mo
aa_bulletin_board/locale/uk/LC_MESSAGES/django.po
aa_bulletin_board/locale/zh_Hans/LC_MESSAGES/django.mo
aa_bulletin_board/locale/zh_Hans/LC_MESSAGES/django.po
aa_bulletin_board/migrations/0001_initial.py
aa_bulletin_board/migrations/0002_alter_bulletin_slug.py
aa_bulletin_board/migrations/0003_group_restrictions.py
aa_bulletin_board/migrations/0004_model_translation.py
aa_bulletin_board-2.5.2.dist-info/METADATA
aa_bulletin_board-2.5.2.dist-info/WHEEL
aa_bulletin_board-2.5.2.dist-info/licenses/LICENSE
aa_bulletin_board-2.5.2.dist-info/RECORD
