Metadata-Version: 2.4
Name: aa-bulletin-board
Version: 2.5.2
Summary: A simple bulletin board for Alliance Auth
Project-URL: Changelog, https://github.com/ppfeufer/aa-bulletin-board/blob/master/CHANGELOG.md
Project-URL: Codecov, https://codecov.io/gh/ppfeufer/aa-bulletin-board
Project-URL: Discord, https://discord.gg/fjnHAmk
Project-URL: Documentation, https://github.com/ppfeufer/aa-bulletin-board/blob/master/README.md
Project-URL: Donation, https://ko-fi.com/ppfeufer
Project-URL: GitHub, https://github.com/ppfeufer/aa-bulletin-board
Project-URL: Tracker, https://github.com/ppfeufer/aa-bulletin-board/issues
Project-URL: Translation, https://weblate.ppfeufer.de/projects/alliance-auth-apps/aa-bulletin-board/
Author-email: Peter Pfeufer <develop@ppfeufer.de>
License:                     GNU GENERAL PUBLIC LICENSE
License-File: LICENSE
Keywords: allianceauth,bulletinboard,eveonline
Classifier: Environment :: Web Environment
Classifier: Framework :: Django
Classifier: Framework :: Django :: 4.2
Classifier: Intended Audience :: Developers
Classifier: License :: OSI Approved :: GNU General Public License v3 (GPLv3)
Classifier: Operating System :: OS Independent
Classifier: Programming Language :: Python
Classifier: Programming Language :: Python :: 3 :: Only
Classifier: Programming Language :: Python :: 3.10
Classifier: Programming Language :: Python :: 3.11
Classifier: Programming Language :: Python :: 3.12
Classifier: Programming Language :: Python :: 3.13
Classifier: Topic :: Internet :: WWW/HTTP
Classifier: Topic :: Internet :: WWW/HTTP :: Dynamic Content
Requires-Python: <3.14,>=3.10
Requires-Dist: allianceauth<5,>=4.6
Requires-Dist: django-ckeditor-5>=0.2.19
Requires-Dist: unidecode
Provides-Extra: tests-allianceauth-latest
Requires-Dist: coverage; extra == 'tests-allianceauth-latest'
Requires-Dist: django-webtest; extra == 'tests-allianceauth-latest'
Requires-Dist: faker; extra == 'tests-allianceauth-latest'
